businessfrance_checker/__init__.py
businessfrance_checker/__main__.py
businessfrance_checker/lib.py
businessfrance_checker-1.0.0.dist-info/licenses/LICENSE
businessfrance_checker-1.0.0.dist-info/METADATA
businessfrance_checker-1.0.0.dist-info/WHEEL
businessfrance_checker-1.0.0.dist-info/top_level.txt
businessfrance_checker-1.0.0.dist-info/RECORD
